AUTHORS.rst
CONTRIBUTING.rst
HISTORY.rst
LICENSE
MANIFEST.in
README.rst
requirements.txt
setup.cfg
setup.py
test_requirements.txt
lib/bettertimeit/__init__.py
lib/bettertimeit/distutils_command.py
lib/bettertimeit.egg-info/PKG-INFO
lib/bettertimeit.egg-info/SOURCES.txt
lib/bettertimeit.egg-info/dependency_links.txt
lib/bettertimeit.egg-info/entry_points.txt
lib/bettertimeit.egg-info/not-zip-safe
lib/bettertimeit.egg-info/requires.txt
lib/bettertimeit.egg-info/top_level.txt