Metadata-Version: 1.1
Name: bettertimeit
Version: 1.1.2
Summary: A Better Timeit
Home-page: https://github.com/simonpercivall/bettertimeit
Author: Simon Percivall
Author-email: percivall@gmail.com
License: BSD
Keywords: bettertimeit
Platform: UNKNOWN
Classifier: Development Status :: 4 - Beta
Classifier: Intended Audience :: Developers
Classifier: License :: OSI Approved :: BSD License
Classifier: Natural Language :: English
Classifier: Programming Language :: Python :: 2
Classifier: Programming Language :: Python :: 2.6
Classifier: Programming Language :: Python :: 2.7
Classifier: Programming Language :: Python :: 3
Classifier: Programming Language :: Python :: 3.3
Classifier: Programming Language :: Python :: 3.4
